[
    {
        "city": "安达韦拉斯",
        "time": "2016年3月",
        "max": "20",
        "min": "2",
        "a_max": "16",
        "a_min": "3",
        "sunny": "0",
        "rainy": "26",
        "cloudy": "5",
        "snowy": "0"
    },
    {
        "city": "安达韦拉斯",
        "time": "2016年2月",
        "max": "19",
        "min": "2",
        "a_max": "16",
        "a_min": "3",
        "sunny": "1",
        "rainy": "26",
        "cloudy": "2",
        "snowy": "0"
    },
    {
        "city": "安达韦拉斯",
        "time": "2016年1月",
        "max": "22",
        "min": "2",
        "a_max": "18",
        "a_min": "3",
        "sunny": "0",
        "rainy": "30",
        "cloudy": "5",
        "snowy": "0"
    },
    {
        "city": "安达韦拉斯",
        "time": "2015年12月",
        "max": "19",
        "min": "2",
        "a_max": "16",
        "a_min": "3",
        "sunny": "0",
        "rainy": "27",
        "cloudy": "5",
        "snowy": "0"
    },
    {
        "city": "安达韦拉斯",
        "time": "2015年11月",
        "max": "21",
        "min": "3",
        "a_max": "17",
        "a_min": "3",
        "sunny": "0",
        "rainy": "23",
        "cloudy": "12",
        "snowy": "0"
    },
    {
        "city": "安达韦拉斯",
        "time": "2015年10月",
        "max": "19",
        "min": "2",
        "a_max": "16",
        "a_min": "3",
        "sunny": "4",
        "rainy": "21",
        "cloudy": "14",
        "snowy": "0"
    },
    {
        "city": "安达韦拉斯",
        "time": "2015年9月",
        "max": "19",
        "min": "-1",
        "a_max": "17",
        "a_min": "2",
        "sunny": "9",
        "rainy": "19",
        "cloudy": "19",
        "snowy": "0"
    },
    {
        "city": "安达韦拉斯",
        "time": "2015年8月",
        "max": "20",
        "min": "-3",
        "a_max": "16",
        "a_min": "0",
        "sunny": "21",
        "rainy": "6",
        "cloudy": "11",
        "snowy": "0"
    },
    {
        "city": "安达韦拉斯",
        "time": "2015年7月",
        "max": "18",
        "min": "-4",
        "a_max": "15",
        "a_min": "-1",
        "sunny": "20",
        "rainy": "5",
        "cloudy": "15",
        "snowy": "0"
    },
    {
        "city": "安达韦拉斯",
        "time": "2015年6月",
        "max": "17",
        "min": "-2",
        "a_max": "15",
        "a_min": "0",
        "sunny": "17",
        "rainy": "3",
        "cloudy": "18",
        "snowy": "0"
    },
    {
        "city": "安达韦拉斯",
        "time": "2015年5月",
        "max": "17",
        "min": "1",
        "a_max": "14",
        "a_min": "2",
        "sunny": "3",
        "rainy": "16",
        "cloudy": "23",
        "snowy": "0"
    },
    {
        "city": "安达韦拉斯",
        "time": "2015年4月",
        "max": "15",
        "min": "3",
        "a_max": "13",
        "a_min": "4",
        "sunny": "0",
        "rainy": "29",
        "cloudy": "5",
        "snowy": "0"
    },
    {
        "city": "安达韦拉斯",
        "time": "2015年3月",
        "max": "17",
        "min": "3",
        "a_max": "14",
        "a_min": "5",
        "sunny": "0",
        "rainy": "31",
        "cloudy": "1",
        "snowy": "0"
    },
    {
        "city": "安达韦拉斯",
        "time": "2015年2月",
        "max": "18",
        "min": "3",
        "a_max": "15",
        "a_min": "4",
        "sunny": "0",
        "rainy": "28",
        "cloudy": "2",
        "snowy": "0"
    },
    {
        "city": "安达韦拉斯",
        "time": "2015年1月",
        "max": "16",
        "min": "3",
        "a_max": "14",
        "a_min": "4",
        "sunny": "0",
        "rainy": "31",
        "cloudy": "2",
        "snowy": "0"
    },
    {
        "city": "安达韦拉斯",
        "time": "2014年12月",
        "max": "19",
        "min": "3",
        "a_max": "15",
        "a_min": "5",
        "sunny": "0",
        "rainy": "31",
        "cloudy": "4",
        "snowy": "0"
    },
    {
        "city": "安达韦拉斯",
        "time": "2014年11月",
        "max": "20",
        "min": "3",
        "a_max": "16",
        "a_min": "4",
        "sunny": "2",
        "rainy": "7",
        "cloudy": "9",
        "snowy": "0"
    },
    {
        "city": "安达韦拉斯",
        "time": "2014年10月",
        "max": "17",
        "min": "3",
        "a_max": "15",
        "a_min": "4",
        "sunny": "0",
        "rainy": "15",
        "cloudy": "7",
        "snowy": "0"
    },
    {
        "city": "安达韦拉斯",
        "time": "2014年9月",
        "max": "17",
        "min": "3",
        "a_max": "14",
        "a_min": "4",
        "sunny": "5",
        "rainy": "18",
        "cloudy": "19",
        "snowy": "0"
    },
    {
        "city": "安达韦拉斯",
        "time": "2014年8月",
        "max": "16",
        "min": "1",
        "a_max": "14",
        "a_min": "2",
        "sunny": "20",
        "rainy": "8",
        "cloudy": "14",
        "snowy": "0"
    },
    {
        "city": "安达韦拉斯",
        "time": "2014年7月",
        "max": "16",
        "min": "1",
        "a_max": "14",
        "a_min": "2",
        "sunny": "11",
        "rainy": "6",
        "cloudy": "24",
        "snowy": "0"
    },
    {
        "city": "安达韦拉斯",
        "time": "2014年6月",
        "max": "18",
        "min": "1",
        "a_max": "15",
        "a_min": "2",
        "sunny": "14",
        "rainy": "0",
        "cloudy": "19",
        "snowy": "0"
    },
    {
        "city": "安达韦拉斯",
        "time": "2014年5月",
        "max": "17",
        "min": "0",
        "a_max": "15",
        "a_min": "3",
        "sunny": "8",
        "rainy": "18",
        "cloudy": "13",
        "snowy": "0"
    },
    {
        "city": "安达韦拉斯",
        "time": "2014年4月",
        "max": "20",
        "min": "4",
        "a_max": "16",
        "a_min": "6",
        "sunny": "2",
        "rainy": "24",
        "cloudy": "8",
        "snowy": "0"
    },
    {
        "city": "安达韦拉斯",
        "time": "2014年3月",
        "max": "19",
        "min": "6",
        "a_max": "16",
        "a_min": "7",
        "sunny": "0",
        "rainy": "28",
        "cloudy": "0",
        "snowy": "0"
    },
    {
        "city": "安达韦拉斯",
        "time": "2014年2月",
        "max": "21",
        "min": "6",
        "a_max": "17",
        "a_min": "8",
        "sunny": "1",
        "rainy": "25",
        "cloudy": "3",
        "snowy": "0"
    },
    {
        "city": "安达韦拉斯",
        "time": "2014年1月",
        "max": "20",
        "min": "8",
        "a_max": "17",
        "a_min": "8",
        "sunny": "0",
        "rainy": "25",
        "cloudy": "4",
        "snowy": "0"
    },
    {
        "city": "安达韦拉斯",
        "time": "2013年12月",
        "max": "22",
        "min": "7",
        "a_max": "18",
        "a_min": "8",
        "sunny": "0",
        "rainy": "25",
        "cloudy": "6",
        "snowy": "0"
    },
    {
        "city": "安达韦拉斯",
        "time": "2013年11月",
        "max": "21",
        "min": "6",
        "a_max": "18",
        "a_min": "8",
        "sunny": "2",
        "rainy": "11",
        "cloudy": "6",
        "snowy": "0"
    }
]